acmd/__init__.py
acmd/compat.py
acmd/config.py
acmd/deploy.py
acmd/logger.py
acmd/main.py
acmd/repo.py
acmd/server.py
acmd/assets/__init__.py
acmd/assets/api.py
acmd/assets/funnel.py
acmd/assets/utils.py
acmd/data/acmd.bash_completion
acmd/data/acmd.rc.template
acmd/jcr/__init__.py
acmd/jcr/path.py
acmd/tools/__init__.py
acmd/tools/asset_tool.py
acmd/tools/bundle.py
acmd/tools/config_tool.py
acmd/tools/groovy.py
acmd/tools/groups.py
acmd/tools/help.py
acmd/tools/install_bash_completion.py
acmd/tools/jcr.py
acmd/tools/package_tool.py
acmd/tools/search.py
acmd/tools/storage.py
acmd/tools/tool_utils.py
acmd/tools/users.py
acmd/tools/workflows.py
acmd/util/__init__.py
acmd/util/crypto.py
acmd/util/groovyconsole.py
acmd/util/html.py
acmd/util/props.py
acmd/util/strings.py
acmd/workflows/__init__.py
acmd/workflows/api.py
aem_cmd-0.14.5.data/scripts/acmd
aem_cmd-0.14.5.dist-info/DESCRIPTION.rst
aem_cmd-0.14.5.dist-info/METADATA
aem_cmd-0.14.5.dist-info/RECORD
aem_cmd-0.14.5.dist-info/WHEEL
aem_cmd-0.14.5.dist-info/metadata.json
aem_cmd-0.14.5.dist-info/top_level.txt
